bauhaus_circular/__init__.py
bauhaus_circular/carbon_calculator.py
bauhaus_circular/climate_analyzer.py
bauhaus_circular/design_optimizer.py
bauhaus_circular/material_analyzer.py
bauhaus_circular_tools-0.2.1.dist-info/licenses/LICENSE
bauhaus_circular_tools-0.2.1.dist-info/METADATA
bauhaus_circular_tools-0.2.1.dist-info/WHEEL
bauhaus_circular_tools-0.2.1.dist-info/top_level.txt
bauhaus_circular_tools-0.2.1.dist-info/RECORD
