Metadata-Version: 2.4
Name: bauhaus-circular-tools
Version: 0.2.1
Summary: Herramientas de diseño circular para arquitectura basadas en principios Bauhaus
Author-email: Mary Magali Villca Cruz <arqmaryvillca@gmail.com>
Maintainer-email: Mary Magali Villca Cruz <arqmaryvillca@gmail.com>
License: MIT
Keywords: bauhaus,circular-design,architecture,sustainability,carbon,rhino,grasshopper,circular-economy,green-building,lca,ladybug-tools
Classifier: Development Status :: 4 - Beta
Classifier: Intended Audience :: Developers
Classifier: Intended Audience :: Science/Research
Classifier: Intended Audience :: End Users/Desktop
Classifier: Topic :: Utilities
Classifier: License :: OSI Approved :: MIT License
Classifier: Programming Language :: Python :: 3
Classifier: Programming Language :: Python :: 3.8
Classifier: Programming Language :: Python :: 3.9
Classifier: Programming Language :: Python :: 3.10
Classifier: Programming Language :: Python :: 3.11
Classifier: Programming Language :: Python :: 3.12
Classifier: Operating System :: OS Independent
Requires-Python: >=3.8
License-File: LICENSE
Requires-Dist: ladybug-core>=0.44.0
Requires-Dist: ladybug-geometry>=1.34.0
Requires-Dist: numpy
Requires-Dist: pandas
Requires-Dist: matplotlib
Provides-Extra: dev
Requires-Dist: pytest>=7.0.0; extra == "dev"
Requires-Dist: pytest-cov>=4.0.0; extra == "dev"
Requires-Dist: black>=22.0.0; extra == "dev"
Requires-Dist: flake8>=5.0.0; extra == "dev"
Requires-Dist: mypy>=0.990; extra == "dev"
Requires-Dist: build>=0.10.0; extra == "dev"
Requires-Dist: twine>=4.0.0; extra == "dev"
Dynamic: license-file
